ergodiff/__init__.py
ergodiff/inner_diff.py
ergodiff/outer_diff.py
ergodiff/preprocess.py
ergodiff/reconstruct.py
ergodiff-0.2.0.dist-info/WHEEL
ergodiff-0.2.0.dist-info/METADATA
ergodiff-0.2.0.dist-info/RECORD
