Metadata-Version: 2.1
Name: ergodiff
Version: 0.2.0
Summary: An ergonomic text-difference pattern generator.
Author: Lingxi Li
Author-email: lilingxi01@gmail.com
Requires-Python: >=3.9,<4.0
Classifier: Programming Language :: Python :: 3
Classifier: Programming Language :: Python :: 3.9
Classifier: Programming Language :: Python :: 3.10
Classifier: Programming Language :: Python :: 3.11
